Workbook

Sheet CLV task
B2: Customer Lifetime Value Analysis
B4: This analysis looks at three months of weekly e-commerce cohort data from November through January to track long-term Customer Lifetime Value (CLV). Key Takeaways: - November Performance: Results were strong across all November cohorts. Driven by Black Week sales, every cohort comfortably surpassed the $2 CAC (Customer Acquisition Cost) threshold. - Holiday Drop: Revenue fell sharply in December. The four cohorts acquired over the holiday period performed particularly poorly, barely reaching a 12-week CLV of $0.50. - January Trend: Sales failed to recover in late January, with CLV remaining consistently below the $2 target. Recommendation: We need an immediate review of our Customer Acquisition strategy. Relying on heavy seasonal promotions like Black Friday to reach profitability isn't a sustainable long-term model for the rest of the year.
A6: Table 1: Weekly Average Revenue by Cohorts
B8: Weeks Since User Registration
A9: Cohort | B9: {=_xlfn.TOROW(_xlfn.UNIQUE(Data!B2:B91))} -> 0 | C9: 1 | D9: 2 | E9: 3 | F9: 4 | G9: 5 | H9: 6 | I9: 7 | J9: 8 | K9: 9 | L9: 10 | M9: 11 | N9: 12
A10: {=_xlfn.UNIQUE(Data!A2:A91)} -> 44136 | B10: {=IFERROR(INDEX(Data!$C:$C, MATCH($A10 & B$9, Data!$A:$A & Data!$B:$B, 0)), 0)} -> 0.93799183 | C10: {=IFERROR(INDEX(Data!$C:$C, MATCH($A10 & C$9, Data!$A:$A & Data!$B:$B, 0)), 0)} -> 0.32637713 | D10: {=IFERROR(INDEX(Data!$C:$C, MATCH($A10 & D$9, Data!$A:$A & Data!$B:$B, 0)), 0)} -> 0.26720789 | E10: {=IFERROR(INDEX(Data!$C:$C, MATCH($A10 & E$9, Data!$A:$A & Data!$B:$B, 0)), 0)} -> 0.26172926 | F10: {=IFERROR(INDEX(Data!$C:$C, MATCH($A10 & F$9, Data!$A:$A & Data!$B:$B, 0)), 0)} -> 0.15987648 | G10: {=IFERROR(INDEX(Data!$C:$C, MATCH($A10 & G$9, Data!$A:$A & Data!$B:$B, 0)), 0)} -> 0.15320251 | H10: {=IFERROR(INDEX(Data!$C:$C, MATCH($A10 & H$9, Data!$A:$A & Data!$B:$B, 0)), 0)} -> 0.16530531 | I10: {=IFERROR(INDEX(Data!$C:$C, MATCH($A10 & I$9, Data!$A:$A & Data!$B:$B, 0)), 0)} -> 0.02500249 | ... N10: {=IFERROR(INDEX(Data!$C:$C, MATCH($A10 & N$9, Data!$A:$A & Data!$B:$B, 0)), 0)} -> 0.018179102 | P10: An increase in registration week revenue was observed in November, peaking in the week of 11/22/2020, which coincides with Black Week. A significant decrease in revenue, throughout all cohorts, was observed in the 4 week period from 12/20/2020, which coincides with the extended Christmas, New Year's period.
A11: 44143 | B11: {=IFERROR(INDEX(Data!$C:$C, MATCH($A11 & B$9, Data!$A:$A & Data!$B:$B, 0)), 0)} -> 1.1919665 | C11: {=IFERROR(INDEX(Data!$C:$C, MATCH($A11 & C$9, Data!$A:$A & Data!$B:$B, 0)), 0)} -> 0.38128388 | D11: {=IFERROR(INDEX(Data!$C:$C, MATCH($A11 & D$9, Data!$A:$A & Data!$B:$B, 0)), 0)} -> 0.2812346 | E11: {=IFERROR(INDEX(Data!$C:$C, MATCH($A11 & E$9, Data!$A:$A & Data!$B:$B, 0)), 0)} -> 0.22930015 | F11: {=IFERROR(INDEX(Data!$C:$C, MATCH($A11 & F$9, Data!$A:$A & Data!$B:$B, 0)), 0)} -> 0.27655249 | G11: {=IFERROR(INDEX(Data!$C:$C, MATCH($A11 & G$9, Data!$A:$A & Data!$B:$B, 0)), 0)} -> 0.10448497 | H11: {=IFERROR(INDEX(Data!$C:$C, MATCH($A11 & H$9, Data!$A:$A & Data!$B:$B, 0)), 0)} -> 0.039366683 | I11: {=IFERROR(INDEX(Data!$C:$C, MATCH($A11 & I$9, Data!$A:$A & Data!$B:$B, 0)), 0)} -> 0.069369147 | ... M11: {=IFERROR(INDEX(Data!$C:$C, MATCH($A11 & M$9, Data!$A:$A & Data!$B:$B, 0)), 0)} -> 0.020515032
A12: 44150 | B12: {=IFERROR(INDEX(Data!$C:$C, MATCH($A12 & B$9, Data!$A:$A & Data!$B:$B, 0)), 0)} -> 1.3817316 | C12: {=IFERROR(INDEX(Data!$C:$C, MATCH($A12 & C$9, Data!$A:$A & Data!$B:$B, 0)), 0)} -> 0.29677781 | D12: {=IFERROR(INDEX(Data!$C:$C, MATCH($A12 & D$9, Data!$A:$A & Data!$B:$B, 0)), 0)} -> 0.21871673 | E12: {=IFERROR(INDEX(Data!$C:$C, MATCH($A12 & E$9, Data!$A:$A & Data!$B:$B, 0)), 0)} -> 0.22757075 | F12: {=IFERROR(INDEX(Data!$C:$C, MATCH($A12 & F$9, Data!$A:$A & Data!$B:$B, 0)), 0)} -> 0.16710563 | G12: {=IFERROR(INDEX(Data!$C:$C, MATCH($A12 & G$9, Data!$A:$A & Data!$B:$B, 0)), 0)} -> 0.025609414 | H12: {=IFERROR(INDEX(Data!$C:$C, MATCH($A12 & H$9, Data!$A:$A & Data!$B:$B, 0)), 0)} -> 0.028803586 | I12: {=IFERROR(INDEX(Data!$C:$C, MATCH($A12 & I$9, Data!$A:$A & Data!$B:$B, 0)), 0)} -> 0.022022976 | ... L12: {=IFERROR(INDEX(Data!$C:$C, MATCH($A12 & L$9, Data!$A:$A & Data!$B:$B, 0)), 0)} -> 0.0044270104
A13: 44157 | B13: {=IFERROR(INDEX(Data!$C:$C, MATCH($A13 & B$9, Data!$A:$A & Data!$B:$B, 0)), 0)} -> 1.6472475 | C13: {=IFERROR(INDEX(Data!$C:$C, MATCH($A13 & C$9, Data!$A:$A & Data!$B:$B, 0)), 0)} -> 0.23588124 | D13: {=IFERROR(INDEX(Data!$C:$C, MATCH($A13 & D$9, Data!$A:$A & Data!$B:$B, 0)), 0)} -> 0.22533992 | E13: {=IFERROR(INDEX(Data!$C:$C, MATCH($A13 & E$9, Data!$A:$A & Data!$B:$B, 0)), 0)} -> 0.1193665 | F13: {=IFERROR(INDEX(Data!$C:$C, MATCH($A13 & F$9, Data!$A:$A & Data!$B:$B, 0)), 0)} -> 0.037021948 | G13: {=IFERROR(INDEX(Data!$C:$C, MATCH($A13 & G$9, Data!$A:$A & Data!$B:$B, 0)), 0)} -> 0.013240312 | H13: {=IFERROR(INDEX(Data!$C:$C, MATCH($A13 & H$9, Data!$A:$A & Data!$B:$B, 0)), 0)} -> 0.0064164587 | I13: {=IFERROR(INDEX(Data!$C:$C, MATCH($A13 & I$9, Data!$A:$A & Data!$B:$B, 0)), 0)} -> 0.010592249 | ... K13: {=IFERROR(INDEX(Data!$C:$C, MATCH($A13 & K$9, Data!$A:$A & Data!$B:$B, 0)), 0)} -> 0.0037683964
A14: 44164 | B14: {=IFERROR(INDEX(Data!$C:$C, MATCH($A14 & B$9, Data!$A:$A & Data!$B:$B, 0)), 0)} -> 1.3194034 | C14: {=IFERROR(INDEX(Data!$C:$C, MATCH($A14 & C$9, Data!$A:$A & Data!$B:$B, 0)), 0)} -> 0.3634214 | D14: {=IFERROR(INDEX(Data!$C:$C, MATCH($A14 & D$9, Data!$A:$A & Data!$B:$B, 0)), 0)} -> 0.24328134 | E14: {=IFERROR(INDEX(Data!$C:$C, MATCH($A14 & E$9, Data!$A:$A & Data!$B:$B, 0)), 0)} -> 0.048019644 | F14: {=IFERROR(INDEX(Data!$C:$C, MATCH($A14 & F$9, Data!$A:$A & Data!$B:$B, 0)), 0)} -> 0.012414169 | G14: {=IFERROR(INDEX(Data!$C:$C, MATCH($A14 & G$9, Data!$A:$A & Data!$B:$B, 0)), 0)} -> 0.022145423 | H14: {=IFERROR(INDEX(Data!$C:$C, MATCH($A14 & H$9, Data!$A:$A & Data!$B:$B, 0)), 0)} -> 0.0060934018 | I14: {=IFERROR(INDEX(Data!$C:$C, MATCH($A14 & I$9, Data!$A:$A & Data!$B:$B, 0)), 0)} -> 0.011959438 | J14: {=IFERROR(INDEX(Data!$C:$C, MATCH($A14 & J$9, Data!$A:$A & Data!$B:$B, 0)), 0)} -> 0.0054113046
A15: 44171 | B15: {=IFERROR(INDEX(Data!$C:$C, MATCH($A15 & B$9, Data!$A:$A & Data!$B:$B, 0)), 0)} -> 1.2025722 | C15: {=IFERROR(INDEX(Data!$C:$C, MATCH($A15 & C$9, Data!$A:$A & Data!$B:$B, 0)), 0)} -> 0.32943817 | D15: {=IFERROR(INDEX(Data!$C:$C, MATCH($A15 & D$9, Data!$A:$A & Data!$B:$B, 0)), 0)} -> 0.081477787 | E15: {=IFERROR(INDEX(Data!$C:$C, MATCH($A15 & E$9, Data!$A:$A & Data!$B:$B, 0)), 0)} -> 0.034415191 | F15: {=IFERROR(INDEX(Data!$C:$C, MATCH($A15 & F$9, Data!$A:$A & Data!$B:$B, 0)), 0)} -> 0.020841498 | G15: {=IFERROR(INDEX(Data!$C:$C, MATCH($A15 & G$9, Data!$A:$A & Data!$B:$B, 0)), 0)} -> 0.026933628 | H15: {=IFERROR(INDEX(Data!$C:$C, MATCH($A15 & H$9, Data!$A:$A & Data!$B:$B, 0)), 0)} -> 0.024404147 | I15: {=IFERROR(INDEX(Data!$C:$C, MATCH($A15 & I$9, Data!$A:$A & Data!$B:$B, 0)), 0)} -> 0.0022088425
A16: 44178 | B16: {=IFERROR(INDEX(Data!$C:$C, MATCH($A16 & B$9, Data!$A:$A & Data!$B:$B, 0)), 0)} -> 1.0082296 | C16: {=IFERROR(INDEX(Data!$C:$C, MATCH($A16 & C$9, Data!$A:$A & Data!$B:$B, 0)), 0)} -> 0.10782014 | D16: {=IFERROR(INDEX(Data!$C:$C, MATCH($A16 & D$9, Data!$A:$A & Data!$B:$B, 0)), 0)} -> 0.040233769 | E16: {=IFERROR(INDEX(Data!$C:$C, MATCH($A16 & E$9, Data!$A:$A & Data!$B:$B, 0)), 0)} -> 0.030215084 | F16: {=IFERROR(INDEX(Data!$C:$C, MATCH($A16 & F$9, Data!$A:$A & Data!$B:$B, 0)), 0)} -> 0.04083012 | G16: {=IFERROR(INDEX(Data!$C:$C, MATCH($A16 & G$9, Data!$A:$A & Data!$B:$B, 0)), 0)} -> 0.029817517 | H16: {=IFERROR(INDEX(Data!$C:$C, MATCH($A16 & H$9, Data!$A:$A & Data!$B:$B, 0)), 0)} -> 0.00039756689
A17: 44185 | B17: {=IFERROR(INDEX(Data!$C:$C, MATCH($A17 & B$9, Data!$A:$A & Data!$B:$B, 0)), 0)} -> 0.36870443 | C17: {=IFERROR(INDEX(Data!$C:$C, MATCH($A17 & C$9, Data!$A:$A & Data!$B:$B, 0)), 0)} -> 0.05384184 | D17: {=IFERROR(INDEX(Data!$C:$C, MATCH($A17 & D$9, Data!$A:$A & Data!$B:$B, 0)), 0)} -> 0.020919798 | E17: {=IFERROR(INDEX(Data!$C:$C, MATCH($A17 & E$9, Data!$A:$A & Data!$B:$B, 0)), 0)} -> 0.023275379 | F17: {=IFERROR(INDEX(Data!$C:$C, MATCH($A17 & F$9, Data!$A:$A & Data!$B:$B, 0)), 0)} -> 0.018003365 | G17: {=IFERROR(INDEX(Data!$C:$C, MATCH($A17 & G$9, Data!$A:$A & Data!$B:$B, 0)), 0)} -> 0.0080762759
A18: 44192 | B18: {=IFERROR(INDEX(Data!$C:$C, MATCH($A18 & B$9, Data!$A:$A & Data!$B:$B, 0)), 0)} -> 0.33907733 | C18: {=IFERROR(INDEX(Data!$C:$C, MATCH($A18 & C$9, Data!$A:$A & Data!$B:$B, 0)), 0)} -> 0.050849507 | D18: {=IFERROR(INDEX(Data!$C:$C, MATCH($A18 & D$9, Data!$A:$A & Data!$B:$B, 0)), 0)} -> 0.0045347361 | E18: {=IFERROR(INDEX(Data!$C:$C, MATCH($A18 & E$9, Data!$A:$A & Data!$B:$B, 0)), 0)} -> 0.020376081 | F18: {=IFERROR(INDEX(Data!$C:$C, MATCH($A18 & F$9, Data!$A:$A & Data!$B:$B, 0)), 0)} -> 0.0059858516
A19: 44199 | B19: {=IFERROR(INDEX(Data!$C:$C, MATCH($A19 & B$9, Data!$A:$A & Data!$B:$B, 0)), 0)} -> 0.22837446 | C19: {=IFERROR(INDEX(Data!$C:$C, MATCH($A19 & C$9, Data!$A:$A & Data!$B:$B, 0)), 0)} -> 0.064283832 | D19: {=IFERROR(INDEX(Data!$C:$C, MATCH($A19 & D$9, Data!$A:$A & Data!$B:$B, 0)), 0)} -> 0.027399666 | E19: {=IFERROR(INDEX(Data!$C:$C, MATCH($A19 & E$9, Data!$A:$A & Data!$B:$B, 0)), 0)} -> 0.0047422499
A20: 44206 | B20: {=IFERROR(INDEX(Data!$C:$C, MATCH($A20 & B$9, Data!$A:$A & Data!$B:$B, 0)), 0)} -> 0.39940332 | C20: {=IFERROR(INDEX(Data!$C:$C, MATCH($A20 & C$9, Data!$A:$A & Data!$B:$B, 0)), 0)} -> 0.058502704 | D20: {=IFERROR(INDEX(Data!$C:$C, MATCH($A20 & D$9, Data!$A:$A & Data!$B:$B, 0)), 0)} -> 0.012446392
A21: 44213 | B21: {=IFERROR(INDEX(Data!$C:$C, MATCH($A21 & B$9, Data!$A:$A & Data!$B:$B, 0)), 0)} -> 0.90318545 | C21: {=IFERROR(INDEX(Data!$C:$C, MATCH($A21 & C$9, Data!$A:$A & Data!$B:$B, 0)), 0)} -> 0.12202868
A22: 44220 | B22: {=IFERROR(INDEX(Data!$C:$C, MATCH($A22 & B$9, Data!$A:$A & Data!$B:$B, 0)), 0)} -> 0.19212679
A23: Average ARPU ($) | B23: =AVERAGE(B10:B22) -> 0.85538573 | C23: =AVERAGE(C10:C22) -> 0.19920886 | D23: =AVERAGE(D10:D22) -> 0.12934478 | E23: =AVERAGE(E10:E22) -> 0.099901028 | F23: =AVERAGE(F10:F22) -> 0.082070173 | G23: =AVERAGE(G10:G22) -> 0.047938756 | H23: =AVERAGE(H10:H22) -> 0.038683879 | I23: =AVERAGE(I10:I22) -> 0.023525857 | ... N23: =AVERAGE(N10:N22) -> 0.018179102
A26: Table 2: Weekly Cumulative Revenue by Cohorts
B28: Weeks Since User Registration
A29: Cohort | B29: {=_xlfn.TOROW(_xlfn.UNIQUE(Data!B2:B91))} -> 0 | C29: 1 | D29: 2 | E29: 3 | F29: 4 | G29: 5 | H29: 6 | I29: 7 | J29: 8 | K29: 9 | L29: 10 | M29: 11 | N29: 12
A30: {=_xlfn.UNIQUE(Data!A2:A91)} -> 44136 | B30: {=IFERROR(INDEX(Data!$D:$D,MATCH($A30&B$29,Data!$A:$A&Data!$B:$B,0)),IF(B$30=0,0,A30))} -> 0.93799183 | C30: {=IFERROR(INDEX(Data!$D:$D,MATCH($A30&C$29,Data!$A:$A&Data!$B:$B,0)),IF(C$30=0,0,B30))} -> 1.264369 | D30: {=IFERROR(INDEX(Data!$D:$D,MATCH($A30&D$29,Data!$A:$A&Data!$B:$B,0)),IF(D$30=0,0,C30))} -> 1.5315769 | E30: {=IFERROR(INDEX(Data!$D:$D,MATCH($A30&E$29,Data!$A:$A&Data!$B:$B,0)),IF(E$30=0,0,D30))} -> 1.7933061 | F30: {=IFERROR(INDEX(Data!$D:$D,MATCH($A30&F$29,Data!$A:$A&Data!$B:$B,0)),IF(F$30=0,0,E30))} -> 1.9531826 | G30: {=IFERROR(INDEX(Data!$D:$D,MATCH($A30&G$29,Data!$A:$A&Data!$B:$B,0)),IF(G$30=0,0,F30))} -> 2.1063851 | H30: {=IFERROR(INDEX(Data!$D:$D,MATCH($A30&H$29,Data!$A:$A&Data!$B:$B,0)),IF(H$30=0,0,G30))} -> 2.2716904 | I30: {=IFERROR(INDEX(Data!$D:$D,MATCH($A30&I$29,Data!$A:$A&Data!$B:$B,0)),IF(I$30=0,0,H30))} -> 2.2966929 | ... N30: {=IFERROR(INDEX(Data!$D:$D,MATCH($A30&N$29,Data!$A:$A&Data!$B:$B,0)),IF(N$30=0,0,M30))} -> 2.3745891 | P30: The November cohorts proved to be the best performing over the long term, up to the Black Week cohort of 11/22/2020. Meanwhile the early results from most recent cohorts doesn't indicate a bounce-back, following the Christmas, New year's slump.
A31: 44143 | B31: {=IFERROR(INDEX(Data!$D:$D,MATCH($A31&B$29,Data!$A:$A&Data!$B:$B,0)),IF(B$30=0,0,A31))} -> 1.1919665 | C31: {=IFERROR(INDEX(Data!$D:$D,MATCH($A31&C$29,Data!$A:$A&Data!$B:$B,0)),IF(C$30=0,0,B31))} -> 1.5732504 | D31: {=IFERROR(INDEX(Data!$D:$D,MATCH($A31&D$29,Data!$A:$A&Data!$B:$B,0)),IF(D$30=0,0,C31))} -> 1.854485 | E31: {=IFERROR(INDEX(Data!$D:$D,MATCH($A31&E$29,Data!$A:$A&Data!$B:$B,0)),IF(E$30=0,0,D31))} -> 2.0837851 | F31: {=IFERROR(INDEX(Data!$D:$D,MATCH($A31&F$29,Data!$A:$A&Data!$B:$B,0)),IF(F$30=0,0,E31))} -> 2.3603376 | G31: {=IFERROR(INDEX(Data!$D:$D,MATCH($A31&G$29,Data!$A:$A&Data!$B:$B,0)),IF(G$30=0,0,F31))} -> 2.4648226 | H31: {=IFERROR(INDEX(Data!$D:$D,MATCH($A31&H$29,Data!$A:$A&Data!$B:$B,0)),IF(H$30=0,0,G31))} -> 2.5041893 | I31: {=IFERROR(INDEX(Data!$D:$D,MATCH($A31&I$29,Data!$A:$A&Data!$B:$B,0)),IF(I$30=0,0,H31))} -> 2.5735584 | ... M31: {=IFERROR(INDEX(Data!$D:$D,MATCH($A31&M$29,Data!$A:$A&Data!$B:$B,0)),IF(M$30=0,0,L31))} -> 2.6415722
A32: 44150 | B32: {=IFERROR(INDEX(Data!$D:$D,MATCH($A32&B$29,Data!$A:$A&Data!$B:$B,0)),IF(B$30=0,0,A32))} -> 1.3817316 | C32: {=IFERROR(INDEX(Data!$D:$D,MATCH($A32&C$29,Data!$A:$A&Data!$B:$B,0)),IF(C$30=0,0,B32))} -> 1.6785094 | D32: {=IFERROR(INDEX(Data!$D:$D,MATCH($A32&D$29,Data!$A:$A&Data!$B:$B,0)),IF(D$30=0,0,C32))} -> 1.8972261 | E32: {=IFERROR(INDEX(Data!$D:$D,MATCH($A32&E$29,Data!$A:$A&Data!$B:$B,0)),IF(E$30=0,0,D32))} -> 2.1247969 | F32: {=IFERROR(INDEX(Data!$D:$D,MATCH($A32&F$29,Data!$A:$A&Data!$B:$B,0)),IF(F$30=0,0,E32))} -> 2.2919025 | G32: {=IFERROR(INDEX(Data!$D:$D,MATCH($A32&G$29,Data!$A:$A&Data!$B:$B,0)),IF(G$30=0,0,F32))} -> 2.3175119 | H32: {=IFERROR(INDEX(Data!$D:$D,MATCH($A32&H$29,Data!$A:$A&Data!$B:$B,0)),IF(H$30=0,0,G32))} -> 2.3463155 | I32: {=IFERROR(INDEX(Data!$D:$D,MATCH($A32&I$29,Data!$A:$A&Data!$B:$B,0)),IF(I$30=0,0,H32))} -> 2.3683385 | ... L32: {=IFERROR(INDEX(Data!$D:$D,MATCH($A32&L$29,Data!$A:$A&Data!$B:$B,0)),IF(L$30=0,0,K32))} -> 2.399944
A33: 44157 | B33: {=IFERROR(INDEX(Data!$D:$D,MATCH($A33&B$29,Data!$A:$A&Data!$B:$B,0)),IF(B$30=0,0,A33))} -> 1.6472475 | C33: {=IFERROR(INDEX(Data!$D:$D,MATCH($A33&C$29,Data!$A:$A&Data!$B:$B,0)),IF(C$30=0,0,B33))} -> 1.8831288 | D33: {=IFERROR(INDEX(Data!$D:$D,MATCH($A33&D$29,Data!$A:$A&Data!$B:$B,0)),IF(D$30=0,0,C33))} -> 2.1084687 | E33: {=IFERROR(INDEX(Data!$D:$D,MATCH($A33&E$29,Data!$A:$A&Data!$B:$B,0)),IF(E$30=0,0,D33))} -> 2.2278352 | F33: {=IFERROR(INDEX(Data!$D:$D,MATCH($A33&F$29,Data!$A:$A&Data!$B:$B,0)),IF(F$30=0,0,E33))} -> 2.2648572 | G33: {=IFERROR(INDEX(Data!$D:$D,MATCH($A33&G$29,Data!$A:$A&Data!$B:$B,0)),IF(G$30=0,0,F33))} -> 2.2780975 | H33: {=IFERROR(INDEX(Data!$D:$D,MATCH($A33&H$29,Data!$A:$A&Data!$B:$B,0)),IF(H$30=0,0,G33))} -> 2.2845139 | I33: {=IFERROR(INDEX(Data!$D:$D,MATCH($A33&I$29,Data!$A:$A&Data!$B:$B,0)),IF(I$30=0,0,H33))} -> 2.2951062 | ... K33: {=IFERROR(INDEX(Data!$D:$D,MATCH($A33&K$29,Data!$A:$A&Data!$B:$B,0)),IF(K$30=0,0,J33))} -> 2.3334522
A34: 44164 | B34: {=IFERROR(INDEX(Data!$D:$D,MATCH($A34&B$29,Data!$A:$A&Data!$B:$B,0)),IF(B$30=0,0,A34))} -> 1.3194034 | C34: {=IFERROR(INDEX(Data!$D:$D,MATCH($A34&C$29,Data!$A:$A&Data!$B:$B,0)),IF(C$30=0,0,B34))} -> 1.6828248 | D34: {=IFERROR(INDEX(Data!$D:$D,MATCH($A34&D$29,Data!$A:$A&Data!$B:$B,0)),IF(D$30=0,0,C34))} -> 1.9261061 | E34: {=IFERROR(INDEX(Data!$D:$D,MATCH($A34&E$29,Data!$A:$A&Data!$B:$B,0)),IF(E$30=0,0,D34))} -> 1.9741258 | F34: {=IFERROR(INDEX(Data!$D:$D,MATCH($A34&F$29,Data!$A:$A&Data!$B:$B,0)),IF(F$30=0,0,E34))} -> 1.9865399 | G34: {=IFERROR(INDEX(Data!$D:$D,MATCH($A34&G$29,Data!$A:$A&Data!$B:$B,0)),IF(G$30=0,0,F34))} -> 2.0086854 | H34: {=IFERROR(INDEX(Data!$D:$D,MATCH($A34&H$29,Data!$A:$A&Data!$B:$B,0)),IF(H$30=0,0,G34))} -> 2.0147788 | I34: {=IFERROR(INDEX(Data!$D:$D,MATCH($A34&I$29,Data!$A:$A&Data!$B:$B,0)),IF(I$30=0,0,H34))} -> 2.0267382 | J34: {=IFERROR(INDEX(Data!$D:$D,MATCH($A34&J$29,Data!$A:$A&Data!$B:$B,0)),IF(J$30=0,0,I34))} -> 2.0321495
A35: 44171 | B35: {=IFERROR(INDEX(Data!$D:$D,MATCH($A35&B$29,Data!$A:$A&Data!$B:$B,0)),IF(B$30=0,0,A35))} -> 1.2025722 | C35: {=IFERROR(INDEX(Data!$D:$D,MATCH($A35&C$29,Data!$A:$A&Data!$B:$B,0)),IF(C$30=0,0,B35))} -> 1.5320104 | D35: {=IFERROR(INDEX(Data!$D:$D,MATCH($A35&D$29,Data!$A:$A&Data!$B:$B,0)),IF(D$30=0,0,C35))} -> 1.6134882 | E35: {=IFERROR(INDEX(Data!$D:$D,MATCH($A35&E$29,Data!$A:$A&Data!$B:$B,0)),IF(E$30=0,0,D35))} -> 1.6479034 | F35: {=IFERROR(INDEX(Data!$D:$D,MATCH($A35&F$29,Data!$A:$A&Data!$B:$B,0)),IF(F$30=0,0,E35))} -> 1.6687449 | G35: {=IFERROR(INDEX(Data!$D:$D,MATCH($A35&G$29,Data!$A:$A&Data!$B:$B,0)),IF(G$30=0,0,F35))} -> 1.6956785 | H35: {=IFERROR(INDEX(Data!$D:$D,MATCH($A35&H$29,Data!$A:$A&Data!$B:$B,0)),IF(H$30=0,0,G35))} -> 1.7200827 | I35: {=IFERROR(INDEX(Data!$D:$D,MATCH($A35&I$29,Data!$A:$A&Data!$B:$B,0)),IF(I$30=0,0,H35))} -> 1.7222915
A36: 44178 | B36: {=IFERROR(INDEX(Data!$D:$D,MATCH($A36&B$29,Data!$A:$A&Data!$B:$B,0)),IF(B$30=0,0,A36))} -> 1.0082296 | C36: {=IFERROR(INDEX(Data!$D:$D,MATCH($A36&C$29,Data!$A:$A&Data!$B:$B,0)),IF(C$30=0,0,B36))} -> 1.1160498 | D36: {=IFERROR(INDEX(Data!$D:$D,MATCH($A36&D$29,Data!$A:$A&Data!$B:$B,0)),IF(D$30=0,0,C36))} -> 1.1562835 | E36: {=IFERROR(INDEX(Data!$D:$D,MATCH($A36&E$29,Data!$A:$A&Data!$B:$B,0)),IF(E$30=0,0,D36))} -> 1.1864986 | F36: {=IFERROR(INDEX(Data!$D:$D,MATCH($A36&F$29,Data!$A:$A&Data!$B:$B,0)),IF(F$30=0,0,E36))} -> 1.2273287 | G36: {=IFERROR(INDEX(Data!$D:$D,MATCH($A36&G$29,Data!$A:$A&Data!$B:$B,0)),IF(G$30=0,0,F36))} -> 1.2571463 | H36: {=IFERROR(INDEX(Data!$D:$D,MATCH($A36&H$29,Data!$A:$A&Data!$B:$B,0)),IF(H$30=0,0,G36))} -> 1.2575438
A37: 44185 | B37: {=IFERROR(INDEX(Data!$D:$D,MATCH($A37&B$29,Data!$A:$A&Data!$B:$B,0)),IF(B$30=0,0,A37))} -> 0.36870443 | C37: {=IFERROR(INDEX(Data!$D:$D,MATCH($A37&C$29,Data!$A:$A&Data!$B:$B,0)),IF(C$30=0,0,B37))} -> 0.42254627 | D37: {=IFERROR(INDEX(Data!$D:$D,MATCH($A37&D$29,Data!$A:$A&Data!$B:$B,0)),IF(D$30=0,0,C37))} -> 0.44346607 | E37: {=IFERROR(INDEX(Data!$D:$D,MATCH($A37&E$29,Data!$A:$A&Data!$B:$B,0)),IF(E$30=0,0,D37))} -> 0.46674145 | F37: {=IFERROR(INDEX(Data!$D:$D,MATCH($A37&F$29,Data!$A:$A&Data!$B:$B,0)),IF(F$30=0,0,E37))} -> 0.48474481 | G37: {=IFERROR(INDEX(Data!$D:$D,MATCH($A37&G$29,Data!$A:$A&Data!$B:$B,0)),IF(G$30=0,0,F37))} -> 0.49282109
A38: 44192 | B38: {=IFERROR(INDEX(Data!$D:$D,MATCH($A38&B$29,Data!$A:$A&Data!$B:$B,0)),IF(B$30=0,0,A38))} -> 0.33907733 | C38: {=IFERROR(INDEX(Data!$D:$D,MATCH($A38&C$29,Data!$A:$A&Data!$B:$B,0)),IF(C$30=0,0,B38))} -> 0.38992684 | D38: {=IFERROR(INDEX(Data!$D:$D,MATCH($A38&D$29,Data!$A:$A&Data!$B:$B,0)),IF(D$30=0,0,C38))} -> 0.39446158 | E38: {=IFERROR(INDEX(Data!$D:$D,MATCH($A38&E$29,Data!$A:$A&Data!$B:$B,0)),IF(E$30=0,0,D38))} -> 0.41483766 | F38: {=IFERROR(INDEX(Data!$D:$D,MATCH($A38&F$29,Data!$A:$A&Data!$B:$B,0)),IF(F$30=0,0,E38))} -> 0.42082351
A39: 44199 | B39: {=IFERROR(INDEX(Data!$D:$D,MATCH($A39&B$29,Data!$A:$A&Data!$B:$B,0)),IF(B$30=0,0,A39))} -> 0.22837446 | C39: {=IFERROR(INDEX(Data!$D:$D,MATCH($A39&C$29,Data!$A:$A&Data!$B:$B,0)),IF(C$30=0,0,B39))} -> 0.29265829 | D39: {=IFERROR(INDEX(Data!$D:$D,MATCH($A39&D$29,Data!$A:$A&Data!$B:$B,0)),IF(D$30=0,0,C39))} -> 0.32005796 | E39: {=IFERROR(INDEX(Data!$D:$D,MATCH($A39&E$29,Data!$A:$A&Data!$B:$B,0)),IF(E$30=0,0,D39))} -> 0.32480021
A40: 44206 | B40: {=IFERROR(INDEX(Data!$D:$D,MATCH($A40&B$29,Data!$A:$A&Data!$B:$B,0)),IF(B$30=0,0,A40))} -> 0.39940332 | C40: {=IFERROR(INDEX(Data!$D:$D,MATCH($A40&C$29,Data!$A:$A&Data!$B:$B,0)),IF(C$30=0,0,B40))} -> 0.45790602 | D40: {=IFERROR(INDEX(Data!$D:$D,MATCH($A40&D$29,Data!$A:$A&Data!$B:$B,0)),IF(D$30=0,0,C40))} -> 0.47035241
A41: 44213 | B41: {=IFERROR(INDEX(Data!$D:$D,MATCH($A41&B$29,Data!$A:$A&Data!$B:$B,0)),IF(B$30=0,0,A41))} -> 0.90318545 | C41: {=IFERROR(INDEX(Data!$D:$D,MATCH($A41&C$29,Data!$A:$A&Data!$B:$B,0)),IF(C$30=0,0,B41))} -> 1.0252141
A42: 44220 | B42: {=IFERROR(INDEX(Data!$D:$D,MATCH($A42&B$29,Data!$A:$A&Data!$B:$B,0)),IF(B$30=0,0,A42))} -> 0.19212679
A43: Average cumulative CLV ($) | B43: =SUM($B$23:B23) -> 0.85538573 | C43: =SUM($B$23:C23) -> 1.0545946 | D43: =SUM($B$23:D23) -> 1.1839394 | E43: =SUM($B$23:E23) -> 1.2838404 | F43: =SUM($B$23:F23) -> 1.3659106 | G43: =SUM($B$23:G23) -> 1.4138493 | H43: =SUM($B$23:H23) -> 1.4525332 | I43: =SUM($B$23:I23) -> 1.4760591 | ... N43: =SUM($B$23:N23) -> 1.5556935
A44: Cumulative CLV Growth (%) | C44: =(C43-B43)/B43 -> 0.23288775 | D44: =(D43-C43)/C43 -> 0.12264882 | E44: =(E43-D43)/D43 -> 0.084380189 | F44: =(F43-E43)/E43 -> 0.063925526 | G44: =(G43-F43)/F43 -> 0.035096555 | H44: =(H43-G43)/G43 -> 0.02736068 | I44: =(I43-H43)/H43 -> 0.016196433 | J44: =(J43-I43)/I43 -> 0.0093176005 | ... N44: =(N43-M43)/M43 -> 0.011823695
A47: Table 3: Weekly Revenue Prediction by Cohorts
B49: Weeks Since User Registration
A50: Cohort | B50: 0 | C50: 1 | D50: 2 | E50: 3 | F50: 4 | G50: 5 | H50: 6 | I50: 7 | J50: 8 | K50: 9 | L50: 10 | M50: 11 | N50: 12
A51: {=_xlfn.UNIQUE(Data!A2:A91)} -> 44136 | B51: {=IFERROR(INDEX(Data!$D:$D,MATCH($A51&B$50,Data!$A:$A&Data!$B:$B,0)),IF(B$50=0,0,A51))} -> 0.93799183 | C51: {=IFERROR(INDEX(Data!$D:$D,MATCH($A51&C$50,Data!$A:$A&Data!$B:$B,0)),IF(C$50=0,0,B51))} -> 1.264369 | D51: {=IFERROR(INDEX(Data!$D:$D,MATCH($A51&D$50,Data!$A:$A&Data!$B:$B,0)),IF(D$50=0,0,C51))} -> 1.5315769 | E51: {=IFERROR(INDEX(Data!$D:$D,MATCH($A51&E$50,Data!$A:$A&Data!$B:$B,0)),IF(E$50=0,0,D51))} -> 1.7933061 | F51: {=IFERROR(INDEX(Data!$D:$D,MATCH($A51&F$50,Data!$A:$A&Data!$B:$B,0)),IF(F$50=0,0,E51))} -> 1.9531826 | G51: {=IFERROR(INDEX(Data!$D:$D,MATCH($A51&G$50,Data!$A:$A&Data!$B:$B,0)),IF(G$50=0,0,F51))} -> 2.1063851 | H51: {=IFERROR(INDEX(Data!$D:$D,MATCH($A51&H$50,Data!$A:$A&Data!$B:$B,0)),IF(H$50=0,0,G51))} -> 2.2716904 | I51: {=IFERROR(INDEX(Data!$D:$D,MATCH($A51&I$50,Data!$A:$A&Data!$B:$B,0)),IF(I$50=0,0,H51))} -> 2.2966929 | ... N51: {=IFERROR(INDEX(Data!$D:$D,MATCH($A51&N$50,Data!$A:$A&Data!$B:$B,0)),IF(N$50=0,0,M51))} -> 2.3745891 | P51: The forecast of the Average Customer Lifetime Value shows that, on average, we can expect a CLV of 1.47 USD, which is not sustainable considering that the acquisition cost alone is 2 USD. The review of Customer Acquisition Strategy is strongly advised.
A52: 44143 | B52: {=IFERROR(INDEX(Data!$D:$D,MATCH($A52&B$50,Data!$A:$A&Data!$B:$B,0)),IF(B$50=0,0,A52))} -> 1.1919665 | C52: {=IFERROR(INDEX(Data!$D:$D,MATCH($A52&C$50,Data!$A:$A&Data!$B:$B,0)),IF(C$50=0,0,B52))} -> 1.5732504 | D52: {=IFERROR(INDEX(Data!$D:$D,MATCH($A52&D$50,Data!$A:$A&Data!$B:$B,0)),IF(D$50=0,0,C52))} -> 1.854485 | E52: {=IFERROR(INDEX(Data!$D:$D,MATCH($A52&E$50,Data!$A:$A&Data!$B:$B,0)),IF(E$50=0,0,D52))} -> 2.0837851 | F52: {=IFERROR(INDEX(Data!$D:$D,MATCH($A52&F$50,Data!$A:$A&Data!$B:$B,0)),IF(F$50=0,0,E52))} -> 2.3603376 | G52: {=IFERROR(INDEX(Data!$D:$D,MATCH($A52&G$50,Data!$A:$A&Data!$B:$B,0)),IF(G$50=0,0,F52))} -> 2.4648226 | H52: {=IFERROR(INDEX(Data!$D:$D,MATCH($A52&H$50,Data!$A:$A&Data!$B:$B,0)),IF(H$50=0,0,G52))} -> 2.5041893 | I52: {=IFERROR(INDEX(Data!$D:$D,MATCH($A52&I$50,Data!$A:$A&Data!$B:$B,0)),IF(I$50=0,0,H52))} -> 2.5735584 | ... M52: {=IFERROR(INDEX(Data!$D:$D,MATCH($A52&M$50,Data!$A:$A&Data!$B:$B,0)),IF(M$50=0,0,L52))} -> 2.6415722 | N52: =M52*(1+N44) -> 2.6728053
A53: 44150 | B53: {=IFERROR(INDEX(Data!$D:$D,MATCH($A53&B$50,Data!$A:$A&Data!$B:$B,0)),IF(B$50=0,0,A53))} -> 1.3817316 | C53: {=IFERROR(INDEX(Data!$D:$D,MATCH($A53&C$50,Data!$A:$A&Data!$B:$B,0)),IF(C$50=0,0,B53))} -> 1.6785094 | D53: {=IFERROR(INDEX(Data!$D:$D,MATCH($A53&D$50,Data!$A:$A&Data!$B:$B,0)),IF(D$50=0,0,C53))} -> 1.8972261 | E53: {=IFERROR(INDEX(Data!$D:$D,MATCH($A53&E$50,Data!$A:$A&Data!$B:$B,0)),IF(E$50=0,0,D53))} -> 2.1247969 | F53: {=IFERROR(INDEX(Data!$D:$D,MATCH($A53&F$50,Data!$A:$A&Data!$B:$B,0)),IF(F$50=0,0,E53))} -> 2.2919025 | G53: {=IFERROR(INDEX(Data!$D:$D,MATCH($A53&G$50,Data!$A:$A&Data!$B:$B,0)),IF(G$50=0,0,F53))} -> 2.3175119 | H53: {=IFERROR(INDEX(Data!$D:$D,MATCH($A53&H$50,Data!$A:$A&Data!$B:$B,0)),IF(H$50=0,0,G53))} -> 2.3463155 | I53: {=IFERROR(INDEX(Data!$D:$D,MATCH($A53&I$50,Data!$A:$A&Data!$B:$B,0)),IF(I$50=0,0,H53))} -> 2.3683385 | ... L53: {=IFERROR(INDEX(Data!$D:$D,MATCH($A53&L$50,Data!$A:$A&Data!$B:$B,0)),IF(L$50=0,0,K53))} -> 2.399944 | M53: =L53*(1+M44) -> 2.4279394 | N53: =M53*(1+N44) -> 2.4566466
A54: 44157 | B54: {=IFERROR(INDEX(Data!$D:$D,MATCH($A54&B$50,Data!$A:$A&Data!$B:$B,0)),IF(B$50=0,0,A54))} -> 1.6472475 | C54: {=IFERROR(INDEX(Data!$D:$D,MATCH($A54&C$50,Data!$A:$A&Data!$B:$B,0)),IF(C$50=0,0,B54))} -> 1.8831288 | D54: {=IFERROR(INDEX(Data!$D:$D,MATCH($A54&D$50,Data!$A:$A&Data!$B:$B,0)),IF(D$50=0,0,C54))} -> 2.1084687 | E54: {=IFERROR(INDEX(Data!$D:$D,MATCH($A54&E$50,Data!$A:$A&Data!$B:$B,0)),IF(E$50=0,0,D54))} -> 2.2278352 | F54: {=IFERROR(INDEX(Data!$D:$D,MATCH($A54&F$50,Data!$A:$A&Data!$B:$B,0)),IF(F$50=0,0,E54))} -> 2.2648572 | G54: {=IFERROR(INDEX(Data!$D:$D,MATCH($A54&G$50,Data!$A:$A&Data!$B:$B,0)),IF(G$50=0,0,F54))} -> 2.2780975 | H54: {=IFERROR(INDEX(Data!$D:$D,MATCH($A54&H$50,Data!$A:$A&Data!$B:$B,0)),IF(H$50=0,0,G54))} -> 2.2845139 | I54: {=IFERROR(INDEX(Data!$D:$D,MATCH($A54&I$50,Data!$A:$A&Data!$B:$B,0)),IF(I$50=0,0,H54))} -> 2.2951062 | ... K54: {=IFERROR(INDEX(Data!$D:$D,MATCH($A54&K$50,Data!$A:$A&Data!$B:$B,0)),IF(K$50=0,0,J54))} -> 2.3334522 | L54: =K54*(1+L44) -> 2.3661849 | M54: =L54*(1+M44) -> 2.3937866 | N54: =M54*(1+N44) -> 2.42209
A55: 44164 | B55: {=IFERROR(INDEX(Data!$D:$D,MATCH($A55&B$50,Data!$A:$A&Data!$B:$B,0)),IF(B$50=0,0,A55))} -> 1.3194034 | C55: {=IFERROR(INDEX(Data!$D:$D,MATCH($A55&C$50,Data!$A:$A&Data!$B:$B,0)),IF(C$50=0,0,B55))} -> 1.6828248 | D55: {=IFERROR(INDEX(Data!$D:$D,MATCH($A55&D$50,Data!$A:$A&Data!$B:$B,0)),IF(D$50=0,0,C55))} -> 1.9261061 | E55: {=IFERROR(INDEX(Data!$D:$D,MATCH($A55&E$50,Data!$A:$A&Data!$B:$B,0)),IF(E$50=0,0,D55))} -> 1.9741258 | F55: {=IFERROR(INDEX(Data!$D:$D,MATCH($A55&F$50,Data!$A:$A&Data!$B:$B,0)),IF(F$50=0,0,E55))} -> 1.9865399 | G55: {=IFERROR(INDEX(Data!$D:$D,MATCH($A55&G$50,Data!$A:$A&Data!$B:$B,0)),IF(G$50=0,0,F55))} -> 2.0086854 | H55: {=IFERROR(INDEX(Data!$D:$D,MATCH($A55&H$50,Data!$A:$A&Data!$B:$B,0)),IF(H$50=0,0,G55))} -> 2.0147788 | I55: {=IFERROR(INDEX(Data!$D:$D,MATCH($A55&I$50,Data!$A:$A&Data!$B:$B,0)),IF(I$50=0,0,H55))} -> 2.0267382 | J55: {=IFERROR(INDEX(Data!$D:$D,MATCH($A55&J$50,Data!$A:$A&Data!$B:$B,0)),IF(J$50=0,0,I55))} -> 2.0321495 | K55: =J55*(1+K44) -> 2.044357 | L55: =K55*(1+L44) -> 2.0730344 | M55: =L55*(1+M44) -> 2.0972164 | N55: =M55*(1+N44) -> 2.1220133
A56: 44171 | B56: {=IFERROR(INDEX(Data!$D:$D,MATCH($A56&B$50,Data!$A:$A&Data!$B:$B,0)),IF(B$50=0,0,A56))} -> 1.2025722 | C56: {=IFERROR(INDEX(Data!$D:$D,MATCH($A56&C$50,Data!$A:$A&Data!$B:$B,0)),IF(C$50=0,0,B56))} -> 1.5320104 | D56: {=IFERROR(INDEX(Data!$D:$D,MATCH($A56&D$50,Data!$A:$A&Data!$B:$B,0)),IF(D$50=0,0,C56))} -> 1.6134882 | E56: {=IFERROR(INDEX(Data!$D:$D,MATCH($A56&E$50,Data!$A:$A&Data!$B:$B,0)),IF(E$50=0,0,D56))} -> 1.6479034 | F56: {=IFERROR(INDEX(Data!$D:$D,MATCH($A56&F$50,Data!$A:$A&Data!$B:$B,0)),IF(F$50=0,0,E56))} -> 1.6687449 | G56: {=IFERROR(INDEX(Data!$D:$D,MATCH($A56&G$50,Data!$A:$A&Data!$B:$B,0)),IF(G$50=0,0,F56))} -> 1.6956785 | H56: {=IFERROR(INDEX(Data!$D:$D,MATCH($A56&H$50,Data!$A:$A&Data!$B:$B,0)),IF(H$50=0,0,G56))} -> 1.7200827 | I56: {=IFERROR(INDEX(Data!$D:$D,MATCH($A56&I$50,Data!$A:$A&Data!$B:$B,0)),IF(I$50=0,0,H56))} -> 1.7222915 | J56: =I56*(1+J44) -> 1.7383391 | K56: =J56*(1+K44) -> 1.7487816 | L56: =K56*(1+L44) -> 1.7733128 | M56: =L56*(1+M44) -> 1.7939986 | N56: =M56*(1+N44) -> 1.8152103
A57: 44178 | B57: {=IFERROR(INDEX(Data!$D:$D,MATCH($A57&B$50,Data!$A:$A&Data!$B:$B,0)),IF(B$50=0,0,A57))} -> 1.0082296 | C57: {=IFERROR(INDEX(Data!$D:$D,MATCH($A57&C$50,Data!$A:$A&Data!$B:$B,0)),IF(C$50=0,0,B57))} -> 1.1160498 | D57: {=IFERROR(INDEX(Data!$D:$D,MATCH($A57&D$50,Data!$A:$A&Data!$B:$B,0)),IF(D$50=0,0,C57))} -> 1.1562835 | E57: {=IFERROR(INDEX(Data!$D:$D,MATCH($A57&E$50,Data!$A:$A&Data!$B:$B,0)),IF(E$50=0,0,D57))} -> 1.1864986 | F57: {=IFERROR(INDEX(Data!$D:$D,MATCH($A57&F$50,Data!$A:$A&Data!$B:$B,0)),IF(F$50=0,0,E57))} -> 1.2273287 | G57: {=IFERROR(INDEX(Data!$D:$D,MATCH($A57&G$50,Data!$A:$A&Data!$B:$B,0)),IF(G$50=0,0,F57))} -> 1.2571463 | H57: {=IFERROR(INDEX(Data!$D:$D,MATCH($A57&H$50,Data!$A:$A&Data!$B:$B,0)),IF(H$50=0,0,G57))} -> 1.2575438 | I57: =H57*(1+I44) -> 1.2779116 | J57: =I57*(1+J44) -> 1.2898186 | K57: =J57*(1+K44) -> 1.2975668 | L57: =K57*(1+L44) -> 1.3157685 | M57: =L57*(1+M44) -> 1.331117 | N57: =M57*(1+N44) -> 1.3468558
A58: 44185 | B58: {=IFERROR(INDEX(Data!$D:$D,MATCH($A58&B$50,Data!$A:$A&Data!$B:$B,0)),IF(B$50=0,0,A58))} -> 0.36870443 | C58: {=IFERROR(INDEX(Data!$D:$D,MATCH($A58&C$50,Data!$A:$A&Data!$B:$B,0)),IF(C$50=0,0,B58))} -> 0.42254627 | D58: {=IFERROR(INDEX(Data!$D:$D,MATCH($A58&D$50,Data!$A:$A&Data!$B:$B,0)),IF(D$50=0,0,C58))} -> 0.44346607 | E58: {=IFERROR(INDEX(Data!$D:$D,MATCH($A58&E$50,Data!$A:$A&Data!$B:$B,0)),IF(E$50=0,0,D58))} -> 0.46674145 | F58: {=IFERROR(INDEX(Data!$D:$D,MATCH($A58&F$50,Data!$A:$A&Data!$B:$B,0)),IF(F$50=0,0,E58))} -> 0.48474481 | G58: {=IFERROR(INDEX(Data!$D:$D,MATCH($A58&G$50,Data!$A:$A&Data!$B:$B,0)),IF(G$50=0,0,F58))} -> 0.49282109 | H58: =G58*(1+H44) -> 0.50630501 | I58: =H58*(1+I44) -> 0.51450534 | J58: =I58*(1+J44) -> 0.5192993 | K58: =J58*(1+K44) -> 0.52241881 | L58: =K58*(1+L44) -> 0.5297471 | M58: =L58*(1+M44) -> 0.53592662 | N58: =M58*(1+N44) -> 0.54226326
A59: 44192 | B59: {=IFERROR(INDEX(Data!$D:$D,MATCH($A59&B$50,Data!$A:$A&Data!$B:$B,0)),IF(B$50=0,0,A59))} -> 0.33907733 | C59: {=IFERROR(INDEX(Data!$D:$D,MATCH($A59&C$50,Data!$A:$A&Data!$B:$B,0)),IF(C$50=0,0,B59))} -> 0.38992684 | D59: {=IFERROR(INDEX(Data!$D:$D,MATCH($A59&D$50,Data!$A:$A&Data!$B:$B,0)),IF(D$50=0,0,C59))} -> 0.39446158 | E59: {=IFERROR(INDEX(Data!$D:$D,MATCH($A59&E$50,Data!$A:$A&Data!$B:$B,0)),IF(E$50=0,0,D59))} -> 0.41483766 | F59: {=IFERROR(INDEX(Data!$D:$D,MATCH($A59&F$50,Data!$A:$A&Data!$B:$B,0)),IF(F$50=0,0,E59))} -> 0.42082351 | G59: =F59*(1+G44) -> 0.43559296 | H59: =G59*(1+H44) -> 0.44751108 | I59: =H59*(1+I44) -> 0.45475917 | J59: =I59*(1+J44) -> 0.45899643 | K59: =J59*(1+K44) -> 0.46175369 | L59: =K59*(1+L44) -> 0.46823099 | M59: =L59*(1+M44) -> 0.47369293 | N59: =M59*(1+N44) -> 0.47929373
A60: 44199 | B60: {=IFERROR(INDEX(Data!$D:$D,MATCH($A60&B$50,Data!$A:$A&Data!$B:$B,0)),IF(B$50=0,0,A60))} -> 0.22837446 | C60: {=IFERROR(INDEX(Data!$D:$D,MATCH($A60&C$50,Data!$A:$A&Data!$B:$B,0)),IF(C$50=0,0,B60))} -> 0.29265829 | D60: {=IFERROR(INDEX(Data!$D:$D,MATCH($A60&D$50,Data!$A:$A&Data!$B:$B,0)),IF(D$50=0,0,C60))} -> 0.32005796 | E60: {=IFERROR(INDEX(Data!$D:$D,MATCH($A60&E$50,Data!$A:$A&Data!$B:$B,0)),IF(E$50=0,0,D60))} -> 0.32480021 | F60: =E60*(1+F44) -> 0.34556323 | G60: =F60*(1+G44) -> 0.35769131 | H60: =G60*(1+H44) -> 0.36747799 | I60: =H60*(1+I44) -> 0.37342982 | J60: =I60*(1+J44) -> 0.37690929 | K60: =J60*(1+K44) -> 0.37917345 | L60: =K60*(1+L44) -> 0.38449234 | M60: =L60*(1+M44) -> 0.38897747 | N60: =M60*(1+N44) -> 0.39357662
A61: 44206 | B61: {=IFERROR(INDEX(Data!$D:$D,MATCH($A61&B$50,Data!$A:$A&Data!$B:$B,0)),IF(B$50=0,0,A61))} -> 0.39940332 | C61: {=IFERROR(INDEX(Data!$D:$D,MATCH($A61&C$50,Data!$A:$A&Data!$B:$B,0)),IF(C$50=0,0,B61))} -> 0.45790602 | D61: {=IFERROR(INDEX(Data!$D:$D,MATCH($A61&D$50,Data!$A:$A&Data!$B:$B,0)),IF(D$50=0,0,C61))} -> 0.47035241 | E61: =D61*(1+E44) -> 0.51004084 | F61: =E61*(1+F44) -> 0.54264547 | G61: =F61*(1+G44) -> 0.56169046 | H61: =G61*(1+H44) -> 0.57705869 | I61: =H61*(1+I44) -> 0.58640498 | J61: =I61*(1+J44) -> 0.59186887 | K61: =J61*(1+K44) -> 0.59542432 | L61: =K61*(1+L44) -> 0.6037767 | ... N61: =M61*(1+N44) -> 0.61804193
A62: 44213 | B62: {=IFERROR(INDEX(Data!$D:$D,MATCH($A62&B$50,Data!$A:$A&Data!$B:$B,0)),IF(B$50=0,0,A62))} -> 0.90318545 | C62: {=IFERROR(INDEX(Data!$D:$D,MATCH($A62&C$50,Data!$A:$A&Data!$B:$B,0)),IF(C$50=0,0,B62))} -> 1.0252141 | D62: =C62*(1+D44) -> 1.1509554 | E62: =D62*(1+E44) -> 1.2480733 | F62: =E62*(1+F44) -> 1.327857 | G62: =F62*(1+G44) -> 1.3744602 | H62: =G62*(1+H44) -> 1.4120664 | I62: =H62*(1+I44) -> 1.4349368 | J62: =I62*(1+J44) -> 1.448307 | K62: =J62*(1+K44) -> 1.4570072 | ... N62: =M62*(1+N44) -> 1.5123526
A63: 44220 | B63: {=IFERROR(INDEX(Data!$D:$D,MATCH($A63&B$50,Data!$A:$A&Data!$B:$B,0)),IF(B$50=0,0,A63))} -> 0.19212679 | C63: =B63*(1+C44) -> 0.23687077 | D63: =C63*(1+D44) -> 0.26592269 | E63: =D63*(1+E44) -> 0.28836129 | F63: =E63*(1+F44) -> 0.30679494 | G63: =F63*(1+G44) -> 0.31756239 | H63: =G63*(1+H44) -> 0.32625111 | I63: =H63*(1+I44) -> 0.33153521 | J63: =I63*(1+J44) -> 0.33462433 | ... N63: =M63*(1+N44) -> 0.34942176
M64: CLV Average ($) | N64: =AVERAGE(N51:N63) -> 1.4696277

Sheet Query

Sheet Data
A1: cohort_week | B1: week_offset | C1: arpu | D1: cumulative_clv
A2: 44136 | B2: 0 | C2: 0.93799183 | D2: 0.93799183
A3: 44136 | B3: 1 | C3: 0.32637713 | D3: 1.264369
A4: 44136 | B4: 2 | C4: 0.26720789 | D4: 1.5315769
A5: 44136 | B5: 3 | C5: 0.26172926 | D5: 1.7933061
A6: 44136 | B6: 4 | C6: 0.15987648 | D6: 1.9531826
A7: 44136 | B7: 5 | C7: 0.15320251 | D7: 2.1063851
A8: 44136 | B8: 6 | C8: 0.16530531 | D8: 2.2716904
A9: 44136 | B9: 7 | C9: 0.02500249 | D9: 2.2966929
A10: 44136 | B10: 8 | C10: 0.0078195039 | D10: 2.3045124
A11: 44136 | B11: 9 | C11: 0.013796195 | D11: 2.3183086
A12: 44136 | B12: 10 | C12: 0.023159677 | D12: 2.3414683
A13: 44136 | B13: 11 | C13: 0.014941727 | D13: 2.35641
... A91: 44220 | B91: 0 | C91: 0.19212679 | D91: 0.19212679
